MANIFEST.in
README.md
pyproject.toml
setup.py
/mnt/c/Users/hidbe/CLionProjects/untitled1/csrc/bindings.cpp
/mnt/c/Users/hidbe/CLionProjects/untitled1/csrc/kde_similarity.cu
csrc/bindings.cpp
csrc/kde_similarity.cu
examples/kde_benchmark.py
examples/kde_gradient_workflow.py
examples/kde_kernel_fit.py
examples/kde_noise_demo.py
examples/kde_segmented_batch_demo.py
examples/kde_segmented_benchmark.py
examples/kde_segmented_demo.py
examples/kde_segmented_denoising_demo.py
examples/kde_segmented_train_demo.py
examples/kde_segmented_visualization.py
examples/kde_train_demo.py
examples/kde_visualization.py
rapidalign/__init__.py
rapidalign/algorithms.py
rapidalign/autograd_kde.py
rapidalign/kde.py
rapidalign/kde_gradients.py
rapidalign/learned_kernel.py
rapidalign.egg-info/PKG-INFO
rapidalign.egg-info/SOURCES.txt
rapidalign.egg-info/dependency_links.txt
rapidalign.egg-info/requires.txt
rapidalign.egg-info/top_level.txt
tests/__init__.py
tests/test_kde_cuda.py
tests/test_kde_gradients.py
tests/test_kde_similarity.py