Metadata-Version: 2.4
Name: rapidalign
Version: 0.2.0
Summary: Differentiable KDE/MMD loss for point clouds
Author: RapidAlign Team
Requires-Python: >=3.9
Requires-Dist: torch>=2.0.0
Dynamic: author
Dynamic: requires-dist
Dynamic: requires-python
Dynamic: summary
